CHANGES.rst
CONTRIBUTORS.rst
MANIFEST.in
README.rst
setup.cfg
setup.py
docs/LICENSE.GPL
docs/LICENSE.txt
src/sc/__init__.py
src/sc/__init__.pyc
src/sc.photogallery.egg-info/PKG-INFO
src/sc.photogallery.egg-info/SOURCES.txt
src/sc.photogallery.egg-info/dependency_links.txt
src/sc.photogallery.egg-info/entry_points.txt
src/sc.photogallery.egg-info/namespace_packages.txt
src/sc.photogallery.egg-info/not-zip-safe
src/sc.photogallery.egg-info/requires.txt
src/sc.photogallery.egg-info/top_level.txt
src/sc/photogallery/__init__.py
src/sc/photogallery/__init__.pyc
src/sc/photogallery/config.py
src/sc/photogallery/config.pyc
src/sc/photogallery/configure.zcml
src/sc/photogallery/content.py
src/sc/photogallery/content.pyc
src/sc/photogallery/controlpanel.py
src/sc/photogallery/controlpanel.pyc
src/sc/photogallery/interfaces.py
src/sc/photogallery/interfaces.pyc
src/sc/photogallery/profiles.zcml
src/sc/photogallery/setuphandlers.py
src/sc/photogallery/setuphandlers.pyc
src/sc/photogallery/testing.py
src/sc/photogallery/testing.pyc
src/sc/photogallery/utils.py
src/sc/photogallery/utils.pyc
src/sc/photogallery/Extensions/Install.py
src/sc/photogallery/Extensions/__init__.py
src/sc/photogallery/browser/__init__.py
src/sc/photogallery/browser/__init__.pyc
src/sc/photogallery/browser/configure.zcml
src/sc/photogallery/browser/scaling.py
src/sc/photogallery/browser/scaling.pyc
src/sc/photogallery/browser/view.py
src/sc/photogallery/browser/view.pyc
src/sc/photogallery/browser/zip.py
src/sc/photogallery/browser/zip.pyc
src/sc/photogallery/browser/static/photogallery.css
src/sc/photogallery/browser/static/photogallery.js
src/sc/photogallery/browser/static/photogallery.js.map
src/sc/photogallery/browser/static/photogallery.png
src/sc/photogallery/browser/static/photogallery_icon.png
src/sc/photogallery/browser/static/tile-photogallery.png
src/sc/photogallery/browser/templates/view.pt
src/sc/photogallery/locales/manual.pot
src/sc/photogallery/locales/plone.pot
src/sc/photogallery/locales/sc.photogallery.pot
src/sc/photogallery/locales/es/LC_MESSAGES/plone.mo
src/sc/photogallery/locales/es/LC_MESSAGES/plone.po
src/sc/photogallery/locales/es/LC_MESSAGES/sc.photogallery.mo
src/sc/photogallery/locales/es/LC_MESSAGES/sc.photogallery.po
src/sc/photogallery/locales/pt_BR/LC_MESSAGES/plone.mo
