Metadata-Version: 1.1
Name: sc.photogallery
Version: 1.0b3
Summary: A Photo Gallery content type with a slideshow view.
Home-page: https://github.com/collective/sc.photogallery
Author: Simples Consutoria
Author-email: produtos@simplesconsultoria.com.br
License: UNKNOWN
Keywords: plone photo gallery content type dexterity
Platform: UNKNOWN
Classifier: Development Status :: 4 - Beta
Classifier: Environment :: Web Environment
Classifier: Framework :: Plone
Classifier: Framework :: Plone :: 4.3
Classifier: Intended Audience :: System Administrators
Classifier: License :: OSI Approved :: GNU General Public License v2 (GPLv2)
Classifier: Operating System :: OS Independent
Classifier: Programming Language :: Python
Classifier: Programming Language :: Python :: 2.7
Classifier: Topic :: Software Development :: Libraries :: Python Modules
